AladdinDask_demo/__init__.py
AladdinDask_demo-0.1.1.dist-info/METADATA
AladdinDask_demo-0.1.1.dist-info/WHEEL
AladdinDask_demo-0.1.1.dist-info/top_level.txt
AladdinDask_demo-0.1.1.dist-info/RECORD
