Metadata-Version: 2.1
Name: AladdinDask-demo
Version: 0.1.1
Summary: Aladdin Dask Cluster
Home-page: UNKNOWN
Author: Muxin Diao
Author-email: muxin.diao@blackrock.com
License: UNKNOWN
Platform: UNKNOWN
